odoo8_addon_transport_information-8.0.0.1.0.99.dev2-py2.7-nspkg.pth
odoo8_addon_transport_information-8.0.0.1.0.99.dev2.dist-info/DESCRIPTION.rst
odoo8_addon_transport_information-8.0.0.1.0.99.dev2.dist-info/METADATA
odoo8_addon_transport_information-8.0.0.1.0.99.dev2.dist-info/RECORD
odoo8_addon_transport_information-8.0.0.1.0.99.dev2.dist-info/WHEEL
odoo8_addon_transport_information-8.0.0.1.0.99.dev2.dist-info/metadata.json
odoo8_addon_transport_information-8.0.0.1.0.99.dev2.dist-info/namespace_packages.txt
odoo8_addon_transport_information-8.0.0.1.0.99.dev2.dist-info/top_level.txt
odoo_addons/transport_information/README.rst
odoo_addons/transport_information/__init__.py
odoo_addons/transport_information/__openerp__.py
odoo_addons/transport_information/model/__init__.py
odoo_addons/transport_information/model/transport_mode.py
odoo_addons/transport_information/model/transport_vehicle.py
odoo_addons/transport_information/security/ir.model.access.csv
odoo_addons/transport_information/static/description/icon.png
odoo_addons/transport_information/view/transport_mode.xml
odoo_addons/transport_information/view/transport_vehicle.xml
